{
   "people": [],
   "workouts": [],
   "metadata": [
   {
      "lot": "video_game",
      "source_id": "Yo-kai Sangokushi",
      "identifier": "60405",
      "source": "igdb",
      "collections": [
        {
          "rank": "0",
          "collection_id": "col_bT5SWej-yqhf",
          "collection_name": "[Series] Yo-Kai Watch",
          "created_on": "2025-08-11T14:51:58.599842Z",
          "creator_user_id": "usr_OKnDiF3prlQq",
          "last_updated_on": "2025-08-11T14:51:58.599842Z",
          "information": {}
        }
      ],
      "reviews": [],
      "seen_history": []
   },
   {
      "lot": "video_game",
      "source_id": "Yo-kai Watch Blasters: Red Cat Corps",
      "identifier": "11659",
      "source": "igdb",
      "collections": [
        {
          "rank": "0",
          "collection_id": "col_bT5SWej-yqhf",
          "collection_name": "[Series] Yo-Kai Watch",
          "created_on": "2025-08-11T14:51:58.599842Z",
          "creator_user_id": "usr_OKnDiF3prlQq",
          "last_updated_on": "2025-08-11T14:51:58.599842Z",
          "information": {}
        }
      ],
      "reviews": [],
      "seen_history": []
   },
   {
      "lot": "video_game",
      "source_id": "Yo-Kai Watch Blasters: White Dog Squad",
      "identifier": "54561",
      "source": "igdb",
      "collections": [
        {
          "rank": "0",
          "collection_id": "col_bT5SWej-yqhf",
          "collection_name": "[Series] Yo-Kai Watch",
          "created_on": "2025-08-11T14:51:58.599842Z",
          "creator_user_id": "usr_OKnDiF3prlQq",
          "last_updated_on": "2025-08-11T14:51:58.599842Z",
          "information": {}
        }
      ],
      "reviews": [],
      "seen_history": []
   },
   {
      "lot": "video_game",
      "source_id": "Yo-Kai Watch Busters: Iron Oni Army",
      "identifier": "54563",
      "source": "igdb",
      "collections": [
        {
          "rank": "0",
          "collection_id": "col_bT5SWej-yqhf",
          "collection_name": "[Series] Yo-Kai Watch",
          "created_on": "2025-08-11T14:51:58.599842Z",
          "creator_user_id": "usr_OKnDiF3prlQq",
          "last_updated_on": "2025-08-11T14:51:58.599842Z",
          "information": {}
        }
      ],
      "reviews": [],
      "seen_history": []
   },
   {
      "lot": "video_game",
      "source_id": "Yo-kai Watch Busters 2: Hihou Densetsu Bambalaya Sword",
      "identifier": "54564",
      "source": "igdb",
      "collections": [
        {
          "rank": "0",
          "collection_id": "col_bT5SWej-yqhf",
          "collection_name": "[Series] Yo-Kai Watch",
          "created_on": "2025-08-11T14:51:58.599842Z",
          "creator_user_id": "usr_OKnDiF3prlQq",
          "last_updated_on": "2025-08-11T14:51:58.599842Z",
          "information": {}
        }
      ],
      "reviews": [],
      "seen_history": []
   },
   {
      "lot": "video_game",
      "source_id": "Yo-kai Watch Busters 2: Hihou Densetsu Banbaraya Magnum",
      "identifier": "136935",
      "source": "igdb",
      "collections": [
        {
          "rank": "0",
          "collection_id": "col_bT5SWej-yqhf",
          "collection_name": "[Series] Yo-Kai Watch",
          "created_on": "2025-08-11T14:51:58.599842Z",
          "creator_user_id": "usr_OKnDiF3prlQq",
          "last_updated_on": "2025-08-11T14:51:58.599842Z",
          "information": {}
        }
      ],
      "reviews": [],
      "seen_history": []
   },
   {
      "lot": "video_game",
      "source_id": "Y School Heroes: Bustlin' School Life",
      "identifier": "144735",
      "source": "igdb",
      "collections": [
        {
          "rank": "0",
          "collection_id": "col_bT5SWej-yqhf",
          "collection_name": "[Series] Yo-Kai Watch",
          "created_on": "2025-08-11T14:51:58.599842Z",
          "creator_user_id": "usr_OKnDiF3prlQq",
          "last_updated_on": "2025-08-11T14:51:58.599842Z",
          "information": {}
        }
      ],
      "reviews": [],
      "seen_history": []
   },
   {
      "lot": "video_game",
      "source_id": "Yo-kai Watch",
      "identifier": "11197",
      "source": "igdb",
      "collections": [
        {
          "rank": "0",
          "collection_id": "col_bT5SWej-yqhf",
          "collection_name": "[Series] Yo-Kai Watch",
          "created_on": "2025-08-11T14:51:58.599842Z",
          "creator_user_id": "usr_OKnDiF3prlQq",
          "last_updated_on": "2025-08-11T14:51:58.599842Z",
          "information": {}
        }
      ],
      "reviews": [],
      "seen_history": []
   },
   {
      "lot": "video_game",
      "source_id": "Yo-Kai Watch 2: Bony Spirits",
      "identifier": "11658",
      "source": "igdb",
      "collections": [
        {
          "rank": "0",
          "collection_id": "col_bT5SWej-yqhf",
          "collection_name": "[Series] Yo-Kai Watch",
          "created_on": "2025-08-11T14:51:58.599842Z",
          "creator_user_id": "usr_OKnDiF3prlQq",
          "last_updated_on": "2025-08-11T14:51:58.599842Z",
          "information": {}
        }
      ],
      "reviews": [],
      "seen_history": []
   },
   {
      "lot": "video_game",
      "source_id": "Yo-Kai Watch 2: Fleshy Souls",
      "identifier": "24470",
      "source": "igdb",
      "collections": [
        {
          "rank": "0",
          "collection_id": "col_bT5SWej-yqhf",
          "collection_name": "[Series] Yo-Kai Watch",
          "created_on": "2025-08-11T14:51:58.599842Z",
          "creator_user_id": "usr_OKnDiF3prlQq",
          "last_updated_on": "2025-08-11T14:51:58.599842Z",
          "information": {}
        }
      ],
      "reviews": [],
      "seen_history": []
   },
   {
      "lot": "video_game",
      "source_id": "Yo-Kai Watch 2: Psychic Specters",
      "identifier": "27129",
      "source": "igdb",
      "collections": [
        {
          "rank": "0",
          "collection_id": "col_bT5SWej-yqhf",
          "collection_name": "[Series] Yo-Kai Watch",
          "created_on": "2025-08-11T14:51:58.599842Z",
          "creator_user_id": "usr_OKnDiF3prlQq",
          "last_updated_on": "2025-08-11T14:51:58.599842Z",
          "information": {}
        }
      ],
      "reviews": [],
      "seen_history": []
   },
   {
      "lot": "video_game",
      "source_id": "Yo-Kai Dictionary",
      "identifier": "57026",
      "source": "igdb",
      "collections": [
        {
          "rank": "0",
          "collection_id": "col_bT5SWej-yqhf",
          "collection_name": "[Series] Yo-Kai Watch",
          "created_on": "2025-08-11T14:51:58.599842Z",
          "creator_user_id": "usr_OKnDiF3prlQq",
          "last_updated_on": "2025-08-11T14:51:58.599842Z",
          "information": {}
        }
      ],
      "reviews": [],
      "seen_history": []
   },
   {
      "lot": "video_game",
      "source_id": "Yo-kai Watch 4",
      "identifier": "96246",
      "source": "igdb",
      "collections": [
        {
          "rank": "0",
          "collection_id": "col_bT5SWej-yqhf",
          "collection_name": "[Series] Yo-Kai Watch",
          "created_on": "2025-08-11T14:51:58.599842Z",
          "creator_user_id": "usr_OKnDiF3prlQq",
          "last_updated_on": "2025-08-11T14:51:58.599842Z",
          "information": {}
        }
      ],
      "reviews": [],
      "seen_history": []
   },
   {
      "lot": "video_game",
      "source_id": "Yo-kai Watch: Medal Wars",
      "identifier": "109272",
      "source": "igdb",
      "collections": [
        {
          "rank": "0",
          "collection_id": "col_bT5SWej-yqhf",
          "collection_name": "[Series] Yo-Kai Watch",
          "created_on": "2025-08-11T14:51:58.599842Z",
          "creator_user_id": "usr_OKnDiF3prlQq",
          "last_updated_on": "2025-08-11T14:51:58.599842Z",
          "information": {}
        }
      ],
      "reviews": [],
      "seen_history": []
   },
   {
      "lot": "video_game",
      "source_id": "Yo-kai Watch 3: Sukiyaki",
      "identifier": "113248",
      "source": "igdb",
      "collections": [
        {
          "rank": "0",
          "collection_id": "col_bT5SWej-yqhf",
          "collection_name": "[Series] Yo-Kai Watch",
          "created_on": "2025-08-11T14:51:58.599842Z",
          "creator_user_id": "usr_OKnDiF3prlQq",
          "last_updated_on": "2025-08-11T14:51:58.599842Z",
          "information": {}
        }
      ],
      "reviews": [],
      "seen_history": []
   },
   {
      "lot": "video_game",
      "source_id": "Yo-kai Watch 3",
      "identifier": "113249",
      "source": "igdb",
      "collections": [
        {
          "rank": "0",
          "collection_id": "col_bT5SWej-yqhf",
          "collection_name": "[Series] Yo-Kai Watch",
          "created_on": "2025-08-11T14:51:58.599842Z",
          "creator_user_id": "usr_OKnDiF3prlQq",
          "last_updated_on": "2025-08-11T14:51:58.599842Z",
          "information": {}
        }
      ],
      "reviews": [],
      "seen_history": []
   },
   {
      "lot": "video_game",
      "source_id": "Yo-kai Watch 4++",
      "identifier": "127255",
      "source": "igdb",
      "collections": [
        {
          "rank": "0",
          "collection_id": "col_bT5SWej-yqhf",
          "collection_name": "[Series] Yo-Kai Watch",
          "created_on": "2025-08-11T14:51:58.599842Z",
          "creator_user_id": "usr_OKnDiF3prlQq",
          "last_updated_on": "2025-08-11T14:51:58.599842Z",
          "information": {}
        }
      ],
      "reviews": [],
      "seen_history": []
   },
   {
      "lot": "video_game",
      "source_id": "Yo-Kai Watch 3: Sushi",
      "identifier": "136889",
      "source": "igdb",
      "collections": [
        {
          "rank": "0",
          "collection_id": "col_bT5SWej-yqhf",
          "collection_name": "[Series] Yo-Kai Watch",
          "created_on": "2025-08-11T14:51:58.599842Z",
          "creator_user_id": "usr_OKnDiF3prlQq",
          "last_updated_on": "2025-08-11T14:51:58.599842Z",
          "information": {}
        }
      ],
      "reviews": [],
      "seen_history": []
   },
   {
      "lot": "video_game",
      "source_id": "Yo-Kai Watch 3: Tempura",
      "identifier": "222295",
      "source": "igdb",
      "collections": [
        {
          "rank": "0",
          "collection_id": "col_bT5SWej-yqhf",
          "collection_name": "[Series] Yo-Kai Watch",
          "created_on": "2025-08-11T14:51:58.599842Z",
          "creator_user_id": "usr_OKnDiF3prlQq",
          "last_updated_on": "2025-08-11T14:51:58.599842Z",
          "information": {}
        }
      ],
      "reviews": [],
      "seen_history": []
   }
  ],
   "exercises": [],
   "measurements": [],
   "metadata_groups": [],
   "workout_templates": []
}