{
   "people": [],
   "workouts": [],
   "metadata": [
   {
      "lot": "video_game",
      "source_id": "Halo Wars 2",
      "identifier": "11570",
      "source": "igdb",
      "collections": [
        {
          "rank": "0",
          "collection_id": "col_bT5SWej-yqhf",
          "collection_name": "[Series] Halo",
          "created_on": "2025-08-11T14:51:58.599842Z",
          "creator_user_id": "usr_OKnDiF3prlQq",
          "last_updated_on": "2025-08-11T14:51:58.599842Z",
          "information": {}
        }
      ],
      "reviews": [],
      "seen_history": []
   },
   {
      "lot": "video_game",
      "source_id": "Halo Wars",
      "identifier": "988",
      "source": "igdb",
      "collections": [
        {
          "rank": "0",
          "collection_id": "col_bT5SWej-yqhf",
          "collection_name": "[Series] Halo",
          "created_on": "2025-08-11T14:51:58.599842Z",
          "creator_user_id": "usr_OKnDiF3prlQq",
          "last_updated_on": "2025-08-11T14:51:58.599842Z",
          "information": {}
        }
      ],
      "reviews": [],
      "seen_history": []
   },
   {
      "lot": "video_game",
      "source_id": "Halo: Combat Evolved",
      "identifier": "740",
      "source": "igdb",
      "collections": [
        {
          "rank": "0",
          "collection_id": "col_bT5SWej-yqhf",
          "collection_name": "[Series] Halo",
          "created_on": "2025-08-11T14:51:58.599842Z",
          "creator_user_id": "usr_OKnDiF3prlQq",
          "last_updated_on": "2025-08-11T14:51:58.599842Z",
          "information": {}
        }
      ],
      "reviews": [],
      "seen_history": []
   },
   {
      "lot": "video_game",
      "source_id": "Halo 2",
      "identifier": "986",
      "source": "igdb",
      "collections": [
        {
          "rank": "0",
          "collection_id": "col_bT5SWej-yqhf",
          "collection_name": "[Series] Halo",
          "created_on": "2025-08-11T14:51:58.599842Z",
          "creator_user_id": "usr_OKnDiF3prlQq",
          "last_updated_on": "2025-08-11T14:51:58.599842Z",
          "information": {}
        }
      ],
      "reviews": [],
      "seen_history": []
   },
   {
      "lot": "video_game",
      "source_id": "Halo 3",
      "identifier": "987",
      "source": "igdb",
      "collections": [
        {
          "rank": "0",
          "collection_id": "col_bT5SWej-yqhf",
          "collection_name": "[Series] Halo",
          "created_on": "2025-08-11T14:51:58.599842Z",
          "creator_user_id": "usr_OKnDiF3prlQq",
          "last_updated_on": "2025-08-11T14:51:58.599842Z",
          "information": {}
        }
      ],
      "reviews": [],
      "seen_history": []
   },
   {
      "lot": "video_game",
      "source_id": "Halo 3: ODST",
      "identifier": "989",
      "source": "igdb",
      "collections": [
        {
          "rank": "0",
          "collection_id": "col_bT5SWej-yqhf",
          "collection_name": "[Series] Halo",
          "created_on": "2025-08-11T14:51:58.599842Z",
          "creator_user_id": "usr_OKnDiF3prlQq",
          "last_updated_on": "2025-08-11T14:51:58.599842Z",
          "information": {}
        }
      ],
      "reviews": [],
      "seen_history": []
   },
   {
      "lot": "video_game",
      "source_id": "Halo: Reach",
      "identifier": "990",
      "source": "igdb",
      "collections": [
        {
          "rank": "0",
          "collection_id": "col_bT5SWej-yqhf",
          "collection_name": "[Series] Halo",
          "created_on": "2025-08-11T14:51:58.599842Z",
          "creator_user_id": "usr_OKnDiF3prlQq",
          "last_updated_on": "2025-08-11T14:51:58.599842Z",
          "information": {}
        }
      ],
      "reviews": [],
      "seen_history": []
   },
   {
      "lot": "video_game",
      "source_id": "Halo 4",
      "identifier": "991",
      "source": "igdb",
      "collections": [
        {
          "rank": "0",
          "collection_id": "col_bT5SWej-yqhf",
          "collection_name": "[Series] Halo",
          "created_on": "2025-08-11T14:51:58.599842Z",
          "creator_user_id": "usr_OKnDiF3prlQq",
          "last_updated_on": "2025-08-11T14:51:58.599842Z",
          "information": {}
        }
      ],
      "reviews": [],
      "seen_history": []
   },
   {
      "lot": "video_game",
      "source_id": "Halo: Combat Evolved Anniversary",
      "identifier": "2640",
      "source": "igdb",
      "collections": [
        {
          "rank": "0",
          "collection_id": "col_bT5SWej-yqhf",
          "collection_name": "[Series] Halo",
          "created_on": "2025-08-11T14:51:58.599842Z",
          "creator_user_id": "usr_OKnDiF3prlQq",
          "last_updated_on": "2025-08-11T14:51:58.599842Z",
          "information": {}
        }
      ],
      "reviews": [],
      "seen_history": []
   },
   {
      "lot": "video_game",
      "source_id": "Halo: Spartan Assault",
      "identifier": "4839",
      "source": "igdb",
      "collections": [
        {
          "rank": "0",
          "collection_id": "col_bT5SWej-yqhf",
          "collection_name": "[Series] Halo",
          "created_on": "2025-08-11T14:51:58.599842Z",
          "creator_user_id": "usr_OKnDiF3prlQq",
          "last_updated_on": "2025-08-11T14:51:58.599842Z",
          "information": {}
        }
      ],
      "reviews": [],
      "seen_history": []
   },
   {
      "lot": "video_game",
      "source_id": "Halo 5: Guardians",
      "identifier": "6803",
      "source": "igdb",
      "collections": [
        {
          "rank": "0",
          "collection_id": "col_bT5SWej-yqhf",
          "collection_name": "[Series] Halo",
          "created_on": "2025-08-11T14:51:58.599842Z",
          "creator_user_id": "usr_OKnDiF3prlQq",
          "last_updated_on": "2025-08-11T14:51:58.599842Z",
          "information": {}
        }
      ],
      "reviews": [],
      "seen_history": []
   },
   {
      "lot": "video_game",
      "source_id": "Halo: Spartan Strike",
      "identifier": "7849",
      "source": "igdb",
      "collections": [
        {
          "rank": "0",
          "collection_id": "col_bT5SWej-yqhf",
          "collection_name": "[Series] Halo",
          "created_on": "2025-08-11T14:51:58.599842Z",
          "creator_user_id": "usr_OKnDiF3prlQq",
          "last_updated_on": "2025-08-11T14:51:58.599842Z",
          "information": {}
        }
      ],
      "reviews": [],
      "seen_history": []
   },
   {
      "lot": "video_game",
      "source_id": "Halo 5: Forge",
      "identifier": "24782",
      "source": "igdb",
      "collections": [
        {
          "rank": "0",
          "collection_id": "col_bT5SWej-yqhf",
          "collection_name": "[Series] Halo",
          "created_on": "2025-08-11T14:51:58.599842Z",
          "creator_user_id": "usr_OKnDiF3prlQq",
          "last_updated_on": "2025-08-11T14:51:58.599842Z",
          "information": {}
        }
      ],
      "reviews": [],
      "seen_history": []
   },
   {
      "lot": "video_game",
      "source_id": "Halo 4: King of the Hill Fueled by Mountain Dew",
      "identifier": "77343",
      "source": "igdb",
      "collections": [
        {
          "rank": "0",
          "collection_id": "col_bT5SWej-yqhf",
          "collection_name": "[Series] Halo",
          "created_on": "2025-08-11T14:51:58.599842Z",
          "creator_user_id": "usr_OKnDiF3prlQq",
          "last_updated_on": "2025-08-11T14:51:58.599842Z",
          "information": {}
        }
      ],
      "reviews": [],
      "seen_history": []
   },
   {
      "lot": "video_game",
      "source_id": "Halo: Fireteam Raven",
      "identifier": "102066",
      "source": "igdb",
      "collections": [
        {
          "rank": "0",
          "collection_id": "col_bT5SWej-yqhf",
          "collection_name": "[Series] Halo",
          "created_on": "2025-08-11T14:51:58.599842Z",
          "creator_user_id": "usr_OKnDiF3prlQq",
          "last_updated_on": "2025-08-11T14:51:58.599842Z",
          "information": {}
        }
      ],
      "reviews": [],
      "seen_history": []
   },
   {
      "lot": "video_game",
      "source_id": "Halo Infinite",
      "identifier": "103281",
      "source": "igdb",
      "collections": [
        {
          "rank": "0",
          "collection_id": "col_bT5SWej-yqhf",
          "collection_name": "[Series] Halo",
          "created_on": "2025-08-11T14:51:58.599842Z",
          "creator_user_id": "usr_OKnDiF3prlQq",
          "last_updated_on": "2025-08-11T14:51:58.599842Z",
          "information": {}
        }
      ],
      "reviews": [],
      "seen_history": []
   },
   {
      "lot": "video_game",
      "source_id": "Halo 2: Anniversary",
      "identifier": "125009",
      "source": "igdb",
      "collections": [
        {
          "rank": "0",
          "collection_id": "col_bT5SWej-yqhf",
          "collection_name": "[Series] Halo",
          "created_on": "2025-08-11T14:51:58.599842Z",
          "creator_user_id": "usr_OKnDiF3prlQq",
          "last_updated_on": "2025-08-11T14:51:58.599842Z",
          "information": {}
        }
      ],
      "reviews": [],
      "seen_history": []
   }
  ],
   "exercises": [],
   "measurements": [],
   "metadata_groups": [],
   "workout_templates": []
}